{
  "type": "Feature",
  "properties": {
    "gn:admin1_code":"10",
    "gn:asciiname":"Ijuw",
    "gn:country_code":"NR",
    "gn:dem":3,
    "gn:feature_class":"P",
    "gn:feature_code":"PPLA",
    "gn:name":"Ijuw",
    "gn:population":180,
    "gn:timezone":"Pacific/Nauru",
    "iso:country":"NR",
    "name:und_x_variant":[
        "Ijuh",
        "Ijub",
        "Ijuw"
    ],
    "wof:name":"Ijuw",
    "wof:placetype":"locality",
    "wof:population":180
},
  "geometry": {"coordinates":[166.95813000000001,-0.521],"type":"Point"}
}